{
  "id2token": {
    "0": "\n",
    "1": " ",
    "2": "!",
    "3": "#",
    "4": "$",
    "5": "%",
    "6": "'",
    "7": "(",
    "8": ")",
    "9": "*",
    "10": "+",
    "11": ",",
    "12": "-",
    "13": ".",
    "14": "/",
    "15": "0",
    "16": "1",
    "17": "2",
    "18": "3",
    "19": "4",
    "20": "5",
    "21": "6",
    "22": "7",
    "23": "8",
    "24": "9",
    "25": ":",
    "26": ";",
    "27": "=",
    "28": "?",
    "29": "@",
    "30": "A",
    "31": "B",
    "32": "C",
    "33": "D",
    "34": "E",
    "35": "F",
    "36": "G",
    "37": "H",
    "38": "I",
    "39": "J",
    "40": "K",
    "41": "L",
    "42": "M",
    "43": "N",
    "44": "O",
    "45": "P",
    "46": "Q",
    "47": "R",
    "48": "S",
    "49": "T",
    "50": "U",
    "51": "V",
    "52": "W",
    "53": "X",
    "54": "Y",
    "55": "Z",
    "56": "\\",
    "57": "^",
    "58": "_",
    "59": "`",
    "60": "a",
    "61": "b",
    "62": "c",
    "63": "d",
    "64": "e",
    "65": "f",
    "66": "g",
    "67": "h",
    "68": "i",
    "69": "j",
    "70": "k",
    "71": "l",
    "72": "m",
    "73": "n",
    "74": "o",
    "75": "p",
    "76": "q",
    "77": "r",
    "78": "s",
    "79": "t",
    "80": "u",
    "81": "v",
    "82": "w",
    "83": "x",
    "84": "y",
    "85": "z",
    "86": "{",
    "87": "|",
    "88": "}",
    "89": "~",
    "90": "<|endoftext|>",
    "91": "<pad>",
    "92": "li",
    "93": "lie",
    "94": "ik",
    "95": "ike",
    "96": "Ro",
    "97": "Rom",
    "98": "us",
    "99": "usc",
    "100": "uscu",
    "101": "uscul",
    "102": "pa",
    "103": "pai",
    "104": "pain",
    "105": "id",
    "106": "ida",
    "107": "iday",
    "108": ".*",
    "109": "ol",
    "110": "olu",
    "111": "olut",
    "112": "ue",
    "113": "ue ",
    "114": "ge",
    "115": "get",
    "116": "geta",
    "117": "me",
    "118": "op",
    "119": "opp",
    "120": "oppe",
    "121": "opped",
    "122": "OG",
    "123": "OGI",
    "124": "st",
    "125": "sto",
    "126": "ta",
    "127": "tai",
    "128": "ve",
    "129": "vel",
    "130": "9,",
    "131": "ow",
    "132": "owe",
    "133": "owev",
    "134": "9 ",
    "135": "ca",
    "136": "can",
    "137": "ym",
    "138": "ymp",
    "139": "ry",
    "140": "ry ",
    "141": "gl",
    "142": "ur",
    "143": "uri",
    "144": "urin",
    "145": "r.",
    "146": "r. ",
    "147": "va",
    "148": "kn",
    "149": "kno",
    "150": "know",
    "151": "un",
    "152": "und",
    "153": "ec",
    "154": "eco",
    "155": "no",
    "156": "not",
    "157": "au",
    "158": "aul",
    "159": "ek",
    "160": ";1",
    "161": "ys",
    "162": "ysi",
    "163": "ysis",
    "164": "ha",
    "165": "han",
    "166": "han ",
    "167": "uc",
    "168": "Ho",
    "169": "Hon",
    "170": "Hong",
    "171": "il",
    "172": "ily",
    "173": "usa",
    "174": "usad",
    "175": "by",
    "176": "gg",
    "177": "gge",
    "178": "gges",
    "179": "ggest",
    "180": "re",
    "181": "red",
    "182": "we",
    "183": "wes",
    "184": "west",
    "185": "da",
    "186": "day",
    "187": " t",
    "188": " th",
    "189": " tha",
    "190": " that",
    "191": "sy",
    "192": "sys",
    "193": "syst",
    "194": "ic",
    "195": "ica",
    "196": "ican",
    "197": "on",
    "198": "oni",
    "199": "onia",
    "200": "mi",
    "201": "min",
    "202": "ig",
    "203": "igr",
    "204": "de",
    "205": "der",
    "206": "deri",
    "207": "tat",
    "208": "tati",
    "209": "gs",
    "210": "eg",
    "211": "ego",
    "212": "egon",
    "213": " o",
    "214": " of",
    "215": " of ",
    "216": "D ",
    "217": "D -",
    "218": "D --",
    "219": "ti",
    "220": "til",
    "221": "till",
    "222": "al",
    "223": "alo",
    "224": "ree",
    "225": "ree ",
    "226": "ga",
    "227": "gam",
    "228": "lo",
    "229": "loc",
    "230": "loci",
    "231": "th",
    "232": "tha",
    "233": "than",
    "234": "1 ",
    "235": "ea",
    "236": "ean",
    "237": "eans",
    "238": "eans ",
    "239": "uch",
    "240": "uch ",
    "241": "uch a",
    "242": "uch as",
    "243": "use",
    "244": "pu",
    "245": "pub"
  },
  "merges": {
    "71,68": 92,
    "92,64": 93,
    "68,70": 94,
    "94,64": 95,
    "47,74": 96,
    "96,72": 97,
    "80,78": 98,
    "98,62": 99,
    "99,80": 100,
    "100,71": 101,
    "75,60": 102,
    "102,68": 103,
    "103,73": 104,
    "68,63": 105,
    "105,60": 106,
    "106,84": 107,
    "13,9": 108,
    "74,71": 109,
    "109,80": 110,
    "110,79": 111,
    "80,64": 112,
    "112,1": 113,
    "66,64": 114,
    "114,79": 115,
    "115,60": 116,
    "72,64": 117,
    "74,75": 118,
    "118,75": 119,
    "119,64": 120,
    "120,63": 121,
    "44,36": 122,
    "122,38": 123,
    "78,79": 124,
    "124,74": 125,
    "79,60": 126,
    "126,68": 127,
    "81,64": 128,
    "128,71": 129,
    "24,11": 130,
    "74,82": 131,
    "131,64": 132,
    "132,81": 133,
    "24,1": 134,
    "62,60": 135,
    "135,73": 136,
    "84,72": 137,
    "137,75": 138,
    "77,84": 139,
    "139,1": 140,
    "66,71": 141,
    "80,77": 142,
    "142,68": 143,
    "143,73": 144,
    "77,13": 145,
    "145,1": 146,
    "81,60": 147,
    "70,73": 148,
    "148,74": 149,
    "149,82": 150,
    "80,73": 151,
    "151,63": 152,
    "64,62": 153,
    "153,74": 154,
    "73,74": 155,
    "155,79": 156,
    "60,80": 157,
    "157,71": 158,
    "64,70": 159,
    "26,16": 160,
    "84,78": 161,
    "161,68": 162,
    "162,78": 163,
    "67,60": 164,
    "164,73": 165,
    "165,1": 166,
    "80,62": 167,
    "37,74": 168,
    "168,73": 169,
    "169,66": 170,
    "68,71": 171,
    "171,84": 172,
    "98,60": 173,
    "173,63": 174,
    "61,84": 175,
    "66,66": 176,
    "176,64": 177,
    "177,78": 178,
    "178,79": 179,
    "77,64": 180,
    "180,63": 181,
    "82,64": 182,
    "182,78": 183,
    "183,79": 184,
    "63,60": 185,
    "185,84": 186,
    "1,79": 187,
    "187,67": 188,
    "188,60": 189,
    "189,79": 190,
    "78,84": 191,
    "191,78": 192,
    "192,79": 193,
    "68,62": 194,
    "194,60": 195,
    "195,73": 196,
    "74,73": 197,
    "197,68": 198,
    "198,60": 199,
    "72,68": 200,
    "200,73": 201,
    "68,66": 202,
    "202,77": 203,
    "63,64": 204,
    "204,77": 205,
    "205,68": 206,
    "126,79": 207,
    "207,68": 208,
    "66,78": 209,
    "64,66": 210,
    "210,74": 211,
    "211,73": 212,
    "1,74": 213,
    "213,65": 214,
    "214,1": 215,
    "33,1": 216,
    "216,12": 217,
    "217,12": 218,
    "79,68": 219,
    "219,71": 220,
    "220,71": 221,
    "60,71": 222,
    "222,74": 223,
    "180,64": 224,
    "224,1": 225,
    "66,60": 226,
    "226,72": 227,
    "71,74": 228,
    "228,62": 229,
    "229,68": 230,
    "79,67": 231,
    "231,60": 232,
    "232,73": 233,
    "16,1": 234,
    "64,60": 235,
    "235,73": 236,
    "236,78": 237,
    "237,1": 238,
    "167,67": 239,
    "239,1": 240,
    "240,60": 241,
    "241,78": 242,
    "98,64": 243,
    "75,80": 244,
    "244,61": 245
  },
  "next_id": 246
}